{
  "smell": "no_api_gateway",
  "model": "mmdutra14_3974/meta-llama/Llama-4-Maverick-17B-128E-Instruct-FP8-e81efef6",
  "diagram": "9-vehicle-tracking-microservices.jpg",
  "confidence": "1",
  "explanation": "The diagram shows an 'API Gateway' component, which is positioned between external clients (IoT devices, Ping, Tracking, Vehicles) and internal services. This indicates that there is a single, unified entry point for external clients, thus avoiding the 'No API Gateway' smell.",
  "involved_services": []
}